llmmd2pdf/__init__.py
llmmd2pdf/app.py
llmmd2pdf/cli.py
llmmd2pdf/static/favicon.svg
llmmd2pdf-0.1.3.dist-info/licenses/LICENSE
llmmd2pdf-0.1.3.dist-info/METADATA
llmmd2pdf-0.1.3.dist-info/WHEEL
llmmd2pdf-0.1.3.dist-info/entry_points.txt
llmmd2pdf-0.1.3.dist-info/top_level.txt
llmmd2pdf-0.1.3.dist-info/RECORD
