Metadata-Version: 2.4
Name: llmmd2pdf
Version: 0.1.3
Summary: A Shiny app to convert LLM Markdown exports to PDF with Quarto
Author: fschwar4
Project-URL: Homepage, https://fschwar4.github.io/llmmd2pdf/
Classifier: Programming Language :: Python :: 3
Classifier: License :: OSI Approved :: GNU Affero General Public License v3
Classifier: Operating System :: OS Independent
Requires-Python: >=3.9
License-File: LICENSE
Requires-Dist: shiny
Requires-Dist: toml
Dynamic: license-file
